nerdchess/__init__.py
nerdchess/board.py
nerdchess/boardmove.py
nerdchess/boardrules.py
nerdchess/config.py
nerdchess/game.py
nerdchess/game_event.py
nerdchess/move.py
nerdchess/pieces.py
nerdchess/player.py
tests/__init__.py
tests/conftest.py
tests/test_board.py
tests/test_game.py
tests/test_moves.py
tests/test_pieces.py
nerdchess-1.0.2.dist-info/METADATA
nerdchess-1.0.2.dist-info/WHEEL
nerdchess-1.0.2.dist-info/top_level.txt
nerdchess-1.0.2.dist-info/RECORD
