Metadata-Version: 2.1
Name: nerdchess
Version: 1.0.2
Summary: A Python chess engine.
Home-page: https://github.com/jwizzle/NerdChess
Author: j wizzle
Author-email: info@hossel.net
License: UNKNOWN
Platform: UNKNOWN
Classifier: Programming Language :: Python :: 3
Classifier: License :: OSI Approved :: MIT License
Classifier: Operating System :: OS Independent
Requires-Python: >=3.6
